{
  "project_info": {
    "project_number": "117027343862",
    "firebase_url": "https://homenumberc2c.firebaseio.com",
    "project_id": "homenumberc2c",
    "storage_bucket": "homenumberc2c.appspot.com"
  },
  "client": [
    {
      "client_info": {
        "mobilesdk_app_id": "1:117027343862:android:44560c2140a7fd3ebacbd7",
        "android_client_info": {
          "package_name": "com.homenumber.print_2"
        }
      },
      "oauth_client": [
        {
          "client_id": "117027343862-4eqlgka78t5i6ftupgil0p81733ojc9h.apps.googleusercontent.com",
          "client_type": 1,
          "android_info": {
            "package_name": "com.homenumber.print_2",
            "certificate_hash": "95f56bccfa3660147b95837a8ee966a9405e8d70"
          }
        },
        {
          "client_id": "117027343862-3or3lrijns4k5lvrfq537fq8rjm5mhrk.apps.googleusercontent.com",
          "client_type": 3
        }
      ],
      "api_key": [
        {
          "current_key": "AIzaSyBLDIV9eg0S2cMmuMzc_WsPzQhNF0rl0Go"
        }
      ],
      "services": {
        "appinvite_service": {
          "other_platform_oauth_client": [
            {
              "client_id": "117027343862-3or3lrijns4k5lvrfq537fq8rjm5mhrk.apps.googleusercontent.com",
              "client_type": 3
            }
          ]
        }
      }
    }
  ],
  "configuration_version": "1"
}